datatrack/__init__.py
datatrack/cli.py
datatrack/diff.py
datatrack/exporter.py
datatrack/history.py
datatrack/linter.py
datatrack/pipeline.py
datatrack/tracker.py
datatrack/verifier.py
datatrack_cli-0.1.0.dist-info/licenses/LICENSE
datatrack_cli-0.1.0.dist-info/METADATA
datatrack_cli-0.1.0.dist-info/WHEEL
datatrack_cli-0.1.0.dist-info/entry_points.txt
datatrack_cli-0.1.0.dist-info/top_level.txt
datatrack_cli-0.1.0.dist-info/RECORD
