Metadata-Version: 2.4
Name: datatrack-cli
Version: 0.1.0
Summary: CLI tool for schema tracking
Author-email: N R Navaneet <navaneetnr@gmail.com>
License: MIT
Project-URL: Homepage, https://github.com/nrnavaneet/datatrack
Project-URL: Bug Tracker, https://github.com/nrnavaneet/datatrack/issues
Classifier: Programming Language :: Python :: 3
Classifier: License :: OSI Approved :: MIT License
Classifier: Operating System :: OS Independent
Classifier: Environment :: Console
Classifier: Intended Audience :: Developers
Classifier: Topic :: Database :: Front-Ends
Classifier: Topic :: Software Development :: Build Tools
Classifier: Topic :: Utilities
Requires-Python: >=3.7
License-File: LICENSE
Requires-Dist: typer[all]
Requires-Dist: PyYAML
Requires-Dist: sqlalchemy
Requires-Dist: psycopg2-binary
Requires-Dist: pymysql
Requires-Dist: pre-commit
Dynamic: license-file
